keep_github_workflows_active/__init__.py
keep_github_workflows_active/__init__conf__.py
keep_github_workflows_active/__main__.py
keep_github_workflows_active/behaviors.py
keep_github_workflows_active/cli.py
keep_github_workflows_active/doctest.env
keep_github_workflows_active/keep_github_workflow_active.py
keep_github_workflows_active/py.typed
keep_github_workflows_active/sanitization.py
keep_github_workflows_active-2.1.2.dist-info/METADATA
keep_github_workflows_active-2.1.2.dist-info/WHEEL
keep_github_workflows_active-2.1.2.dist-info/entry_points.txt
keep_github_workflows_active-2.1.2.dist-info/licenses/LICENSE
keep_github_workflows_active-2.1.2.dist-info/RECORD
