Metadata-Version: 2.4
Name: keep_github_workflows_active
Version: 2.1.2
Summary: Template for python apps with registered cli commands
Project-URL: Homepage, https://github.com/bitranox/keep_github_workflows_active
Project-URL: Repository, https://github.com/bitranox/keep_github_workflows_active.git
Project-URL: Issues, https://github.com/bitranox/keep_github_workflows_active/issues
Author-email: bitranox <bitranox@gmail.com>
License: MIT
License-File: LICENSE
Keywords: ansi,cli,logging,rich,terminal
Classifier: Environment :: Console
Classifier: License :: OSI Approved :: MIT License
Classifier: Operating System :: OS Independent
Classifier: Programming Language :: Python :: 3
Classifier: Programming Language :: Python :: 3 :: Only
Classifier: Typing :: Typed
Requires-Python: >=3.13
Requires-Dist: lib-cli-exit-tools>=2.2.2
Requires-Dist: pydantic>=2.12.5
Requires-Dist: requests>=2.32.5
Requires-Dist: rich-click>=1.9.4
Provides-Extra: dev
Requires-Dist: bandit>=1.9.2; extra == 'dev'
Requires-Dist: build>=1.3.0; extra == 'dev'
Requires-Dist: codecov-cli>=11.2.6; extra == 'dev'
Requires-Dist: import-linter>=2.9; extra == 'dev'
Requires-Dist: pip-audit>=2.10.0; extra == 'dev'
Requires-Dist: pyright>=1.1.407; extra == 'dev'
Requires-Dist: pytest-cov>=7.0.0; extra == 'dev'
Requires-Dist: pytest>=9.0.2; extra == 'dev'
Requires-Dist: rtoml>=0.13.0; extra == 'dev'
Requires-Dist: ruff>=0.14.9; extra == 'dev'
Requires-Dist: textual>=6.9.0; extra == 'dev'
Requires-Dist: twine>=6.2.0; extra == 'dev'
